{
  "language": "Português",
  "success": "Sucesso",
  "cancel": "Cancelar",
  "missingFields": "Preencha todos os campos obrigatórios",
  "errorMessage": "Ocorreu um erro, tente novamente mais tarde",
  "sidebar": {
    "overview": "Visão Geral",
    "products": "Produtos",
    "sales": "Vendas",
    "customers": "Clientes",
    "import": "Importar"
  },
  "auth": {
    "login": "Entrar",
    "signup": "Cadastrar",
    "name": "Nome",
    "surname": "Sobrenome",
    "email": "E-mail",
    "password": "Senha",
    "confirmPassword": "Confirmar Senha",
    "forgotPassword": "Esqueceu sua senha?",
    "resetPassword": "Redefinir Senha",
    "passwordLengthWarning": "A senha deve ter pelo menos 6 caracteres",
    "mismatchPassword": "As senhas não coincidem",
    "invalidEmail": "E-mail inválido",
    "invalidPassword": "Senha inválida",
    "invalidCredentials": "Credenciais inválidas",
    "dontHaveAccount": "Não tem uma conta?",
    "alreadyHaveAccount": "Já tem uma conta?",
    "emailAlreadyRegistered": "Email já cadastrado"
  },
  "modules": {
    "sales": {
      "title": "Vendas",
      "description": "Visualize insights detalhados sobre suas vendas",
      "icon": "pi pi-shopping-cart",
      "add": "Adicionar Venda",
      "edit": "Editar Venda",
      "delete": "Deletar Venda",
      "search": "Pesquisar por vendas",
      "noData": "Nenhuma venda cadastrado, crie ou importe para visualizar os dados",
      "deleteConfirmation": "Tem certeza que deseja deletar esta venda?"
    },
    "products": {
      "title": "Produtos",
      "description": "Visualize insights detalhados sobre seus produtos",
      "icon": "pi pi-box",
      "add": "Adicionar Produto",
      "edit": "Editar Produto",
      "delete": "Deletar Produto",
      "search": "Pesquisar por produtos",
      "noData": "Nenhum produto cadastrado, crie ou importe para visualizar os dados",
      "deleteConfirmation": "Tem certeza que deseja deletar este produto?"
    }
  },
  "time": {
    "year": "Ano",
    "month": "Mês",
    "week": "Semana",
    "day": "Dia",
    "hour": "Hora",
    "minute": "Minuto",
    "second": "Segundo"
  },
  "import": {
    "title": "Importar",
    "description": "Importar dados",
    "uploadPlaceholder": "Arraste e solte ou clique para fazer upload de sua planilha",
    "selectModulePlaceholder": "Selecionar tipo de dados",
    "buttonLabel": "Importar"
  },
  "productsDict": {
    "cards": {
      "products": "Produtos cadastrados",
      "categories": "Categorias",
      "sold": "Produtos vendidos este mês",
      "review": "Nota média dos produtos"
    },
    "soldProducts": {
      "title": "Produtos mais vendidos",
      "description": "Visualize os produtos vendidos por período"
    },
    "productsTable": {
      "title": "Todos os produtos",
      "description": "Visualize e gerencie seus produtos"
    },
    "categoriesSection": {
      "title": "Categorias",
      "description": "Visualize as categorias de seus produtos"
    }
  }
}
